typeracerScraper_package/__init__.py
typeracerScraper_package/typeracerScraper.py
typeRacerScraper_pkg_Mohammad_Kheir-0.0.1.dist-info/LICENSE
typeRacerScraper_pkg_Mohammad_Kheir-0.0.1.dist-info/METADATA
typeRacerScraper_pkg_Mohammad_Kheir-0.0.1.dist-info/WHEEL
typeRacerScraper_pkg_Mohammad_Kheir-0.0.1.dist-info/top_level.txt
typeRacerScraper_pkg_Mohammad_Kheir-0.0.1.dist-info/RECORD
